treescript_diff/__init__.py
treescript_diff/__main__.py
treescript_diff/dictionary_files_diff.py
treescript_diff/diff_trees.py
treescript_diff/input/__init__.py
treescript_diff/input/argument_data.py
treescript_diff/input/argument_parser.py
treescript_diff/input/file_validation.py
treescript_diff/input/input_data.py
treescript_diff-0.1.3.dist-info/licenses/LICENSE
treescript_diff-0.1.3.dist-info/METADATA
treescript_diff-0.1.3.dist-info/WHEEL
treescript_diff-0.1.3.dist-info/entry_points.txt
treescript_diff-0.1.3.dist-info/top_level.txt
treescript_diff-0.1.3.dist-info/RECORD
